{"name":"create-many","group":"create-vm","metadata":{"n":"20"},"timers":{"finished":"2024-04-11T15:57:40.75325321+02:00","started":"2024-04-11T15:54:09.286997698+02:00","vm-running":"2024-04-11T15:57:03.608021767+02:00"},"metrics":[{"name":"opennebula-control-1","cpu":{"cores":[0.0199,0,0.0396,0.01,0.0297],"average":0.019840000000000003},"ram":0.0807434,"disk":0.012,"timestamp":"2024-04-11T13:53:59Z"},{"name":"opennebula-control-1","cpu":{"cores":[0.0226,0,0,0.05,0.0404],"average":0.0226},"ram":0.0807431,"disk":0.008,"timestamp":"2024-04-11T13:54:01Z"},{"name":"opennebula-control-1","cpu":{"cores":[0.0273,0.05,0.05,0,0.0098],"average":0.027420000000000007},"ram":0.0807722,"disk":0.352,"timestamp":"2024-04-11T13:54:03Z"},{"name":"opennebula-control-1","cpu":{"cores":[0.0251,0.05,0.05,0,0],"average":0.025019999999999997},"ram":0.0807722,"disk":0.016,"timestamp":"2024-04-11T13:54:05Z"},{"name":"opennebula-control-1","cpu":{"cores":[0.0226,0,0,0.0495,0.0404],"average":0.0225},"ram":0.0807722,"disk":0.008,"timestamp":"2024-04-11T13:54:07Z"},{"name":"opennebula-control-1","cpu":{"cores":[0.6784,0.63,0.7172,0.71,0.6566],"average":0.6784399999999999},"ram":0.083409,"disk":0.008,"timestamp":"2024-04-11T13:54:10Z"},{"name":"opennebula-control-1","cpu":{"cores":[0.895,0.88,0.92,0.88,0.9],"average":0.8949999999999999},"ram":0.110978,"disk":0.024,"timestamp":"2024-04-11T13:54:12Z"},{"name":"opennebula-control-1","cpu":{"cores":[0.1378,0.1386,0.1287,0.1616,0.1224],"average":0.13782},"ram":0.110547,"disk":0.976,"timestamp":"2024-04-11T13:54:14Z"},{"name":"opennebula-control-1","cpu":{"cores":[0.6725,0.6436,0.6238,0.7327,0.69],"average":0.67252},"ram":0.0826246,"disk":0.004,"timestamp":"2024-04-11T13:54:16Z"},{"name":"opennebula-control-1","cpu":{"cores":[0.9225,0.92,0.94,0.9,0.93],"average":0.9225},"ram":0.110577,"disk":0.004,"timestamp":"2024-04-11T13:54:18Z"},{"name":"opennebula-control-1","cpu":{"cores":[0.8557,0.88,0.8218,0.8614,0.86],"average":0.85578},"ram":0.124081,"disk":0.008,"timestamp":"2024-04-11T13:54:20Z"},{"name":"opennebula-control-1","cpu":{"cores":[0.8325,0.83,0.8283,0.7723,0.9],"average":0.83262},"ram":0.0881915,"disk":0.004,"timestamp":"2024-04-11T13:54:23Z"},{"name":"opennebula-control-1","cpu":{"cores":[0.9002,0.9109,0.9,0.89,0.9],"average":0.90022},"ram":0.112555,"disk":0.616,"timestamp":"2024-04-11T13:54:25Z"},{"name":"opennebula-control-1","cpu":{"cores":[0.7481,0.81,0.8081,0.7576,0.6162],"average":0.748},"ram":0.120611,"disk":0.832,"timestamp":"2024-04-11T13:54:27Z"},{"name":"opennebula-control-1","cpu":{"cores":[0.5312,0.2727,0.802,0.7822,0.26],"average":0.5296200000000001},"ram":0.0958576,"disk":0.072,"timestamp":"2024-04-11T13:54:29Z"},{"name":"opennebula-control-1","cpu":{"cores":[0.92,0.94,0.92,0.9,0.92],"average":0.9199999999999999},"ram":0.113444,"disk":0.032,"timestamp":"2024-04-11T13:54:32Z"},{"name":"opennebula-control-1","cpu":{"cores":[0.8404,0.83,0.8416,0.8283,0.8614],"average":0.84034},"ram":0.121524,"disk":0.1592,"timestamp":"2024-04-11T13:54:34Z"},{"name":"opennebula-control-1","cpu":{"cores":[0.81,0.7778,0.8416,0.8,0.82],"average":0.80988},"ram":0.0900238,"disk":0.12,"timestamp":"2024-04-11T13:54:36Z"},{"name":"opennebula-control-1","cpu":{"cores":[0.9075,0.89,0.91,0.93,0.9],"average":0.9075000000000001},"ram":0.112665,"disk":0.008,"timestamp":"2024-04-11T13:54:38Z"},{"name":"opennebula-control-1","cpu":{"cores":[0.8571,0.89,0.84,0.8586,0.84],"average":0.85714},"ram":0.117284,"disk":0.012,"timestamp":"2024-04-11T13:54:41Z"},{"name":"opennebula-control-1","cpu":{"cores":[0.8396,0.82,0.8788,0.87,0.79],"average":0.8396800000000001},"ram":0.0924078,"disk":0.104,"timestamp":"2024-04-11T13:54:43Z"},{"name":"opennebula-control-1","cpu":{"cores":[0.6334,0.8911,0.8218,0.5253,0.29],"average":0.63232},"ram":0.111488,"disk":0.148,"timestamp":"2024-04-11T13:54:45Z"},{"name":"opennebula-control-1","cpu":{"cores":[0.6493,0.83,0.34,0.5446,0.8812],"average":0.6490199999999999},"ram":0.115883,"disk":0.012,"timestamp":"2024-04-11T13:54:47Z"},{"name":"opennebula-control-1","cpu":{"cores":[0.7469,0.7723,0.6465,0.8,0.7677],"average":0.74668},"ram":0.0925156,"disk":0.148,"timestamp":"2024-04-11T13:54:50Z"},{"name":"opennebula-control-1","cpu":{"cores":[0.8922,0.8889,0.87,0.92,0.89],"average":0.89222},"ram":0.112112,"disk":0.184,"timestamp":"2024-04-11T13:54:52Z"},{"name":"opennebula-control-1","cpu":{"cores":[0.8781,0.92,0.8614,0.87,0.8614],"average":0.8781800000000001},"ram":0.116864,"disk":0.008,"timestamp":"2024-04-11T13:54:54Z"},{"name":"opennebula-control-1","cpu":{"cores":[0.8557,0.9,0.83,0.8812,0.8119],"average":0.8557599999999999},"ram":0.0958933,"disk":0.008,"timestamp":"2024-04-11T13:54:56Z"},{"name":"opennebula-control-1","cpu":{"cores":[0.8653,0.84,0.8614,0.87,0.89],"average":0.86534},"ram":0.0994072,"disk":0.008,"timestamp":"2024-04-11T13:54:58Z"},{"name":"opennebula-control-1","cpu":{"cores":[0.7588,0.8,0.73,0.7755,0.73],"average":0.7588600000000001},"ram":0.105154,"disk":0.84,"timestamp":"2024-04-11T13:55:01Z"},{"name":"opennebula-control-1","cpu":{"cores":[0.8756,0.87,0.8911,0.93,0.8119],"average":0.87572},"ram":0.109681,"disk":1,"timestamp":"2024-04-11T13:55:03Z"},{"name":"opennebula-control-1","cpu":{"cores":[0.5746,0.3465,0.32,0.72,0.9109],"average":0.5744},"ram":0.12138,"disk":0.008,"timestamp":"2024-04-11T13:55:05Z"},{"name":"opennebula-control-1","cpu":{"cores":[0.7538,0.72,0.7677,0.7576,0.77],"average":0.75382},"ram":0.0847962,"disk":0.184,"timestamp":"2024-04-11T13:55:08Z"},{"name":"opennebula-control-1","cpu":{"cores":[0.9125,0.9,0.93,0.9,0.92],"average":0.9125},"ram":0.108105,"disk":0.004,"timestamp":"2024-04-11T13:55:10Z"},{"name":"opennebula-control-1","cpu":{"cores":[0.7318,0.7551,0.7228,0.75,0.7],"average":0.73194},"ram":0.103938,"disk":0.056,"timestamp":"2024-04-11T13:55:12Z"},{"name":"opennebula-control-1","cpu":{"cores":[0.8831,0.9208,0.8515,0.8812,0.8788],"average":0.88308},"ram":0.103,"disk":0.008,"timestamp":"2024-04-11T13:55:14Z"},{"name":"opennebula-control-1","cpu":{"cores":[0.8753,0.85,0.87,0.89,0.8911],"average":0.8752800000000001},"ram":0.10803,"disk":0.3287,"timestamp":"2024-04-11T13:55:17Z"},{"name":"opennebula-control-1","cpu":{"cores":[0.5686,0.3069,0.17,0.89,0.91],"average":0.5690999999999999},"ram":0.106341,"disk":0.008,"timestamp":"2024-04-11T13:55:19Z"},{"name":"opennebula-control-1","cpu":{"cores":[0.8831,0.8614,0.89,0.9,0.8812],"average":0.88314},"ram":0.103433,"disk":0.004,"timestamp":"2024-04-11T13:55:21Z"},{"name":"opennebula-control-1","cpu":{"cores":[0.7437,0.6667,0.75,0.8182,0.74],"average":0.74372},"ram":0.0909551,"disk":0.184,"timestamp":"2024-04-11T13:55:23Z"},{"name":"opennebula-control-1","cpu":{"cores":[0.8955,0.9109,0.8788,0.8614,0.9307],"average":0.8954600000000001},"ram":0.10396,"disk":0.004,"timestamp":"2024-04-11T13:55:26Z"},{"name":"opennebula-control-1","cpu":{"cores":[0.8189,0.8515,0.79,0.8416,0.7921],"average":0.81882},"ram":0.0953993,"disk":0.008,"timestamp":"2024-04-11T13:55:28Z"},{"name":"opennebula-control-1","cpu":{"cores":[0.875,0.91,0.88,0.8283,0.8812],"average":0.8749},"ram":0.0976056,"disk":0.004,"timestamp":"2024-04-11T13:55:30Z"},{"name":"opennebula-control-1","cpu":{"cores":[0.8514,0.8182,0.8687,0.87,0.8485],"average":0.85136},"ram":0.0883149,"disk":0.004,"timestamp":"2024-04-11T13:55:32Z"},{"name":"opennebula-control-1","cpu":{"cores":[0.7444,0.92,0.88,0.7677,0.41],"average":0.7444200000000001},"ram":0.0993123,"disk":1,"timestamp":"2024-04-11T13:55:34Z"},{"name":"opennebula-control-1","cpu":{"cores":[0.599,0.6162,0.7172,0.51,0.5545],"average":0.59938},"ram":0.115197,"disk":0.372,"timestamp":"2024-04-11T13:55:37Z"},{"name":"opennebula-control-1","cpu":{"cores":[0.9055,0.93,0.9307,0.88,0.8812],"average":0.9054800000000001},"ram":0.097666,"disk":0.032,"timestamp":"2024-04-11T13:55:40Z"},{"name":"opennebula-control-1","cpu":{"cores":[0.47,0.56,0.4646,0.3883,0.4694],"average":0.47046},"ram":0.10608,"disk":1,"timestamp":"2024-04-11T13:55:42Z"},{"name":"opennebula-control-1","cpu":{"cores":[0.795,0.802,0.8,0.83,0.7475],"average":0.7949},"ram":0.0877891,"disk":0.084,"timestamp":"2024-04-11T13:55:44Z"},{"name":"opennebula-control-1","cpu":{"cores":[0.8675,0.8416,0.87,0.87,0.8889],"average":0.8676},"ram":0.0981273,"disk":0.04,"timestamp":"2024-04-11T13:55:46Z"},{"name":"opennebula-control-1","cpu":{"cores":[0.8722,0.86,0.87,0.8586,0.9],"average":0.87216},"ram":0.0904059,"disk":0.012,"timestamp":"2024-04-11T13:55:48Z"},{"name":"opennebula-control-1","cpu":{"cores":[0.8015,0.75,0.7273,0.8889,0.84],"average":0.8015399999999999},"ram":0.0900993,"disk":0.008,"timestamp":"2024-04-11T13:55:51Z"},{"name":"opennebula-control-1","cpu":{"cores":[0.7412,0.67,0.66,0.8061,0.83],"average":0.74146},"ram":0.0940458,"disk":0.756,"timestamp":"2024-04-11T13:55:53Z"},{"name":"opennebula-control-1","cpu":{"cores":[0.5398,0.5446,0.11,0.66,0.8416],"average":0.5392},"ram":0.0966386,"disk":0.044,"timestamp":"2024-04-11T13:55:55Z"},{"name":"opennebula-control-1","cpu":{"cores":[0.7714,0.7374,0.7755,0.8137,0.7576],"average":0.77112},"ram":0.0954328,"disk":0.004,"timestamp":"2024-04-11T13:55:57Z"},{"name":"opennebula-control-1","cpu":{"cores":[0.8603,0.87,0.86,0.9,0.8119],"average":0.86044},"ram":0.0920439,"disk":0.14,"timestamp":"2024-04-11T13:56:00Z"},{"name":"opennebula-control-1","cpu":{"cores":[0.8772,0.8812,0.8788,0.87,0.8788],"average":0.8772},"ram":0.0898574,"disk":0.044,"timestamp":"2024-04-11T13:56:02Z"},{"name":"opennebula-control-1","cpu":{"cores":[0.8342,0.7723,0.8713,0.802,0.8911],"average":0.8341800000000001},"ram":0.0891468,"disk":0.212,"timestamp":"2024-04-11T13:56:04Z"},{"name":"opennebula-control-1","cpu":{"cores":[0.8266,0.79,0.82,0.8367,0.86],"average":0.8266600000000001},"ram":0.088433,"disk":0.012,"timestamp":"2024-04-11T13:56:06Z"},{"name":"opennebula-control-1","cpu":{"cores":[0.8496,0.8485,0.86,0.81,0.88],"average":0.84962},"ram":0.0851399,"disk":0.656,"timestamp":"2024-04-11T13:56:08Z"},{"name":"opennebula-control-1","cpu":{"cores":[0.5647,0.67,0.3663,0.3366,0.89],"average":0.56552},"ram":0.093763,"disk":0.004,"timestamp":"2024-04-11T13:56:11Z"},{"name":"opennebula-control-1","cpu":{"cores":[0.7431,0.5743,0.81,0.75,0.84],"average":0.74348},"ram":0.0945861,"disk":0.004,"timestamp":"2024-04-11T13:56:13Z"},{"name":"opennebula-control-1","cpu":{"cores":[0.8521,0.82,0.87,0.85,0.8687],"average":0.8521599999999999},"ram":0.0912644,"disk":1,"timestamp":"2024-04-11T13:56:15Z"},{"name":"opennebula-control-1","cpu":{"cores":[0.3885,0.3366,0.4,0.3838,0.4343],"average":0.38864},"ram":0.0998425,"disk":0.58,"timestamp":"2024-04-11T13:56:18Z"},{"name":"opennebula-control-1","cpu":{"cores":[0.9,0.9,0.89,0.91,0.9],"average":0.9},"ram":0.0929234,"disk":0.156,"timestamp":"2024-04-11T13:56:20Z"},{"name":"opennebula-control-1","cpu":{"cores":[0.8894,0.9082,0.9,0.86,0.89],"average":0.8895199999999999},"ram":0.0867131,"disk":0.068,"timestamp":"2024-04-11T13:56:22Z"},{"name":"opennebula-control-1","cpu":{"cores":[0.7864,0.8515,0.7778,0.75,0.7653],"average":0.7862},"ram":0.086804,"disk":0.016,"timestamp":"2024-04-11T13:56:24Z"},{"name":"opennebula-control-1","cpu":{"cores":[0.58,0.52,0.6931,0.57,0.5354],"average":0.5797000000000001},"ram":0.0880551,"disk":0.236,"timestamp":"2024-04-11T13:56:26Z"},{"name":"opennebula-control-1","cpu":{"cores":[0.7456,0.8,0.64,0.89,0.6535],"average":0.7458199999999999},"ram":0.0947095,"disk":0.004,"timestamp":"2024-04-11T13:56:29Z"},{"name":"opennebula-control-1","cpu":{"cores":[0.7412,0.66,0.7071,0.798,0.8],"average":0.7412599999999999},"ram":0.0903739,"disk":0.08,"timestamp":"2024-04-11T13:56:31Z"},{"name":"opennebula-control-1","cpu":{"cores":[0.6341,0.6837,0.4554,0.8515,0.5455],"average":0.63404},"ram":0.0865814,"disk":0.084,"timestamp":"2024-04-11T13:56:33Z"},{"name":"opennebula-control-1","cpu":{"cores":[0.5112,0.71,0.4752,0.45,0.41],"average":0.5112800000000001},"ram":0.083946,"disk":0.2,"timestamp":"2024-04-11T13:56:35Z"},{"name":"opennebula-control-1","cpu":{"cores":[0.5038,0.2828,0.6869,0.505,0.54],"average":0.5037},"ram":0.0854034,"disk":0.004,"timestamp":"2024-04-11T13:56:37Z"},{"name":"opennebula-control-1","cpu":{"cores":[0.4637,0.3366,0.68,0.2626,0.5758],"average":0.46374000000000004},"ram":0.0841751,"disk":0.012,"timestamp":"2024-04-11T13:56:40Z"},{"name":"opennebula-control-1","cpu":{"cores":[0.5362,0.5455,0.703,0.4,0.495],"average":0.53594},"ram":0.082806,"disk":0.636,"timestamp":"2024-04-11T13:56:42Z"},{"name":"opennebula-control-1","cpu":{"cores":[0.5661,0.6078,0.6,0.46,0.596],"average":0.56598},"ram":0.0891881,"disk":0.004,"timestamp":"2024-04-11T13:56:44Z"},{"name":"opennebula-control-1","cpu":{"cores":[0.5651,0.6346,0.505,0.76,0.3627],"average":0.56548},"ram":0.08463,"disk":0.076,"timestamp":"2024-04-11T13:56:46Z"},{"name":"opennebula-control-1","cpu":{"cores":[0.398,0.4242,0.7347,0.3039,0.1327],"average":0.39870000000000005},"ram":0.0869434,"disk":0.516,"timestamp":"2024-04-11T13:56:48Z"},{"name":"opennebula-control-1","cpu":{"cores":[0.2095,0.14,0.32,0.3301,0.0408],"average":0.20808},"ram":0.0814425,"disk":0.692,"timestamp":"2024-04-11T13:56:51Z"},{"name":"opennebula-control-1","cpu":{"cores":[0.2825,0.2727,0.39,0.2727,0.1961],"average":0.2828},"ram":0.0815796,"disk":0.048,"timestamp":"2024-04-11T13:56:53Z"},{"name":"opennebula-control-1","cpu":{"cores":[0.2419,0.1188,0.1089,0.505,0.2347],"average":0.24186000000000002},"ram":0.0819927,"disk":0.008,"timestamp":"2024-04-11T13:56:55Z"},{"name":"opennebula-control-1","cpu":{"cores":[0.2633,0.23,0.3267,0.3469,0.1458],"average":0.26254},"ram":0.0816681,"disk":0.492,"timestamp":"2024-04-11T13:56:57Z"},{"name":"opennebula-control-1","cpu":{"cores":[0.3241,0.2316,0.4646,0.1961,0.402],"average":0.32367999999999997},"ram":0.0865073,"disk":0.004,"timestamp":"2024-04-11T13:56:59Z"},{"name":"opennebula-control-1","cpu":{"cores":[0.2598,0.4057,0.0962,0.3861,0.1443],"average":0.25842},"ram":0.0827287,"disk":0.16,"timestamp":"2024-04-11T13:57:01Z"},{"name":"opennebula-control-1","cpu":{"cores":[0.5464,0.5455,0.4706,0.5354,0.6364],"average":0.54686},"ram":0.0821734,"disk":0.008,"timestamp":"2024-04-11T13:57:03Z"},{"name":"opennebula-control-1","cpu":{"cores":[0.9,0.8889,0.901,0.94,0.87],"average":0.8999799999999999},"ram":0.109533,"disk":0.224,"timestamp":"2024-04-11T13:57:06Z"},{"name":"opennebula-control-1","cpu":{"cores":[0.6834,0.6566,0.6238,0.7755,0.68],"average":0.68386},"ram":0.114605,"disk":0.596,"timestamp":"2024-04-11T13:57:08Z"},{"name":"opennebula-control-1","cpu":{"cores":[0.4527,0.4314,0.42,0.54,0.42],"average":0.45282},"ram":0.107542,"disk":0.132,"timestamp":"2024-04-11T13:57:10Z"},{"name":"opennebula-control-1","cpu":{"cores":[0.515,0.6832,0.32,0.48,0.5758],"average":0.5147999999999999},"ram":0.147498,"disk":0.276,"timestamp":"2024-04-11T13:57:12Z"},{"name":"opennebula-control-1","cpu":{"cores":[0.4812,0.8283,0.3267,0.5152,0.26],"average":0.4822800000000001},"ram":0.158246,"disk":0.004,"timestamp":"2024-04-11T13:57:15Z"},{"name":"opennebula-control-1","cpu":{"cores":[0.5075,0.67,0.47,0.5545,0.3333],"average":0.50706},"ram":0.156669,"disk":0.996,"timestamp":"2024-04-11T13:57:17Z"},{"name":"opennebula-control-1","cpu":{"cores":[0.4838,0.46,0.46,0.495,0.52],"average":0.48376},"ram":0.14954,"disk":0,"timestamp":"2024-04-11T13:57:20Z"},{"name":"opennebula-control-1","cpu":{"cores":[0.3684,0.42,0.1616,0.45,0.44],"average":0.368},"ram":0.129173,"disk":0.004,"timestamp":"2024-04-11T13:57:22Z"},{"name":"opennebula-control-1","cpu":{"cores":[0.5654,0.5743,0.5545,0.5545,0.5784],"average":0.5654199999999999},"ram":0.15117,"disk":0.9412,"timestamp":"2024-04-11T13:57:25Z"},{"name":"opennebula-control-1","cpu":{"cores":[0.4963,0.596,0.5347,0.59,0.2673],"average":0.49686},"ram":0.158427,"disk":0.068,"timestamp":"2024-04-11T13:57:27Z"},{"name":"opennebula-control-1","cpu":{"cores":[0.5815,0.53,0.4444,0.71,0.64],"average":0.58118},"ram":0.146662,"disk":0.908,"timestamp":"2024-04-11T13:57:29Z"},{"name":"opennebula-control-1","cpu":{"cores":[0.5025,0.7129,0.3627,0.4356,0.5],"average":0.50274},"ram":0.135919,"disk":0.004,"timestamp":"2024-04-11T13:57:32Z"},{"name":"opennebula-control-1","cpu":{"cores":[0.495,0.2376,0.9109,0.6733,0.1584],"average":0.4950399999999999},"ram":0.113831,"disk":0.004,"timestamp":"2024-04-11T13:57:34Z"},{"name":"opennebula-control-1","cpu":{"cores":[0.8775,0.9,0.85,0.87,0.89],"average":0.8775000000000001},"ram":0.116062,"disk":0.016,"timestamp":"2024-04-11T13:57:36Z"},{"name":"opennebula-control-1","cpu":{"cores":[0.8722,0.86,0.8889,0.86,0.88],"average":0.8722200000000001},"ram":0.118685,"disk":0.008,"timestamp":"2024-04-11T13:57:39Z"},{"name":"opennebula-control-1","cpu":{"cores":[0.0203,0.0408,0.0404,0,0],"average":0.020300000000000002},"ram":0.0802594,"disk":0.16,"timestamp":"2024-04-11T13:57:41Z"},{"name":"opennebula-control-1","cpu":{"cores":[0.025,0,0.0099,0.05,0.04],"average":0.024980000000000002},"ram":0.0803095,"disk":0.064,"timestamp":"2024-04-11T13:57:43Z"},{"name":"opennebula-control-1","cpu":{"cores":[0.025,0,0,0.0495,0.0495],"average":0.024800000000000003},"ram":0.0803249,"disk":0.012,"timestamp":"2024-04-11T13:57:45Z"},{"name":"opennebula-control-1","cpu":{"cores":[0.0275,0.0404,0.0594,0,0.01],"average":0.027460000000000002},"ram":0.0803251,"disk":0.016,"timestamp":"2024-04-11T13:57:47Z"},{"name":"opennebula-control-1","cpu":{"cores":[0.03,0,0.01,0.05,0.06],"average":0.03},"ram":0.0803249,"disk":0.012,"timestamp":"2024-04-11T13:57:49Z"},{"name":"opennebula-worker-1","cpu":{"cores":[0.0175,0.01,0.02,0.0099,0.03],"average":0.017480000000000002},"ram":0.0238877,"disk":0.012,"timestamp":"2024-04-11T13:54:00Z"},{"name":"opennebula-worker-1","cpu":{"cores":[0.06,0.0297,0.09,0.0099,0.1122],"average":0.06035999999999999},"ram":0.023994,"disk":0.012,"timestamp":"2024-04-11T13:54:02Z"},{"name":"opennebula-worker-1","cpu":{"cores":[0.0574,0.13,0,0.0404,0.0588],"average":0.05732},"ram":0.023787,"disk":0.012,"timestamp":"2024-04-11T13:54:04Z"},{"name":"opennebula-worker-1","cpu":{"cores":[0.0251,0.05,0.0404,0,0.01],"average":0.0251},"ram":0.0238794,"disk":0.016,"timestamp":"2024-04-11T13:54:06Z"},{"name":"opennebula-worker-1","cpu":{"cores":[0.03,0.05,0.06,0.01,0],"average":0.030000000000000006},"ram":0.0239713,"disk":0.016,"timestamp":"2024-04-11T13:54:08Z"},{"name":"opennebula-worker-1","cpu":{"cores":[0.0251,0.0505,0.05,0,0],"average":0.025119999999999996},"ram":0.0233321,"disk":0.54,"timestamp":"2024-04-11T13:54:10Z"},{"name":"opennebula-worker-1","cpu":{"cores":[0.0201,0,0,0.04,0.0404],"average":0.0201},"ram":0.0234638,"disk":0.02,"timestamp":"2024-04-11T13:54:12Z"},{"name":"opennebula-worker-1","cpu":{"cores":[0.0578,0.0101,0,0.18,0.0404],"average":0.05766},"ram":0.0236002,"disk":0.008,"timestamp":"2024-04-11T13:54:14Z"},{"name":"opennebula-worker-1","cpu":{"cores":[0.0251,0.0408,0.05,0,0.0099],"average":0.02516},"ram":0.0233433,"disk":0.068,"timestamp":"2024-04-11T13:54:16Z"},{"name":"opennebula-worker-1","cpu":{"cores":[0.0249,0,0,0.05,0.05],"average":0.02498},"ram":0.0233888,"disk":0.008,"timestamp":"2024-04-11T13:54:19Z"},{"name":"opennebula-worker-1","cpu":{"cores":[0.0224,0.0495,0.04,0,0],"average":0.02238},"ram":0.023304,"disk":0.128,"timestamp":"2024-04-11T13:54:21Z"},{"name":"opennebula-worker-1","cpu":{"cores":[0.0249,0,0,0.0495,0.0495],"average":0.02478},"ram":0.0234426,"disk":0.02,"timestamp":"2024-04-11T13:54:23Z"},{"name":"opennebula-worker-1","cpu":{"cores":[0.0473,0.1212,0.03,0.0098,0.0297],"average":0.0476},"ram":0.0234885,"disk":0.008,"timestamp":"2024-04-11T13:54:25Z"},{"name":"opennebula-worker-1","cpu":{"cores":[0.0302,0.0202,0,0.06,0.0408],"average":0.03024},"ram":0.0245047,"disk":0.04,"timestamp":"2024-04-11T13:54:27Z"},{"name":"opennebula-worker-1","cpu":{"cores":[0.0226,0,0,0.0495,0.04],"average":0.022420000000000002},"ram":0.0237503,"disk":0.008,"timestamp":"2024-04-11T13:54:29Z"},{"name":"opennebula-worker-1","cpu":{"cores":[0.0251,0.01,0,0.0404,0.05],"average":0.0251},"ram":0.0246227,"disk":0.008,"timestamp":"2024-04-11T13:54:31Z"},{"name":"opennebula-worker-1","cpu":{"cores":[0.0591,0.0769,0.0303,0.068,0.06],"average":0.05886},"ram":0.0247059,"disk":0.056,"timestamp":"2024-04-11T13:54:33Z"},{"name":"opennebula-worker-1","cpu":{"cores":[0.2188,0.1959,0.0707,0.42,0.1856],"average":0.2182},"ram":0.0255308,"disk":0.14,"timestamp":"2024-04-11T13:54:35Z"},{"name":"opennebula-worker-1","cpu":{"cores":[0.04,0.04,0.09,0.03,0],"average":0.039999999999999994},"ram":0.0318408,"disk":0.004,"timestamp":"2024-04-11T13:54:37Z"},{"name":"opennebula-worker-1","cpu":{"cores":[0.0277,0.0202,0.0404,0.0505,0],"average":0.027759999999999996},"ram":0.0346248,"disk":0.796,"timestamp":"2024-04-11T13:54:40Z"},{"name":"opennebula-worker-1","cpu":{"cores":[0.025,0,0.0099,0.05,0.04],"average":0.024980000000000002},"ram":0.0343686,"disk":0.008,"timestamp":"2024-04-11T13:54:42Z"},{"name":"opennebula-worker-1","cpu":{"cores":[0.0202,0,0,0.0404,0.0404],"average":0.020200000000000003},"ram":0.0344299,"disk":0.012,"timestamp":"2024-04-11T13:54:44Z"},{"name":"opennebula-worker-1","cpu":{"cores":[0.0599,0.05,0.049,0.1287,0.0102],"average":0.05955999999999999},"ram":0.0344299,"disk":0.036,"timestamp":"2024-04-11T13:54:46Z"},{"name":"opennebula-worker-1","cpu":{"cores":[0.0251,0.05,0.0404,0,0.01],"average":0.0251},"ram":0.0337773,"disk":0.008,"timestamp":"2024-04-11T13:54:48Z"},{"name":"opennebula-worker-1","cpu":{"cores":[0.1025,0.1111,0.1584,0.0792,0.0606],"average":0.10236},"ram":0.0348523,"disk":0.256,"timestamp":"2024-04-11T13:54:50Z"},{"name":"opennebula-worker-1","cpu":{"cores":[0.0687,0.0297,0.0619,0.1031,0.0816],"average":0.06899999999999999},"ram":0.0357399,"disk":0.572,"timestamp":"2024-04-11T13:54:52Z"},{"name":"opennebula-worker-1","cpu":{"cores":[0.0331,0.051,0,0.0412,0.0404],"average":0.033139999999999996},"ram":0.0430052,"disk":0.136,"timestamp":"2024-04-11T13:54:54Z"},{"name":"opennebula-worker-1","cpu":{"cores":[0.0505,0.0306,0.1224,0.01,0.04],"average":0.0507},"ram":0.0434461,"disk":0.068,"timestamp":"2024-04-11T13:54:56Z"},{"name":"opennebula-worker-1","cpu":{"cores":[0.025,0,0,0.0495,0.05],"average":0.024900000000000002},"ram":0.0435263,"disk":0.72,"timestamp":"2024-04-11T13:54:58Z"},{"name":"opennebula-worker-1","cpu":{"cores":[0.02,0.03,0.0099,0.03,0.01],"average":0.01998},"ram":0.0435688,"disk":0.056,"timestamp":"2024-04-11T13:55:01Z"},{"name":"opennebula-worker-1","cpu":{"cores":[0.04,0.099,0.0303,0.0297,0],"average":0.0398},"ram":0.043826,"disk":0,"timestamp":"2024-04-11T13:55:03Z"},{"name":"opennebula-worker-1","cpu":{"cores":[0.0226,0,0,0.04,0.0505],"average":0.02262},"ram":0.0430787,"disk":0.012,"timestamp":"2024-04-11T13:55:05Z"},{"name":"opennebula-worker-1","cpu":{"cores":[0.0827,0.06,0.1111,0.0101,0.1485],"average":0.08248},"ram":0.0431247,"disk":0.064,"timestamp":"2024-04-11T13:55:07Z"},{"name":"opennebula-worker-1","cpu":{"cores":[0.081,0.0505,0.04,0.051,0.1837],"average":0.08124},"ram":0.0457986,"disk":0.324,"timestamp":"2024-04-11T13:55:09Z"},{"name":"opennebula-worker-1","cpu":{"cores":[0.05,0.04,0.1212,0.03,0.0099],"average":0.05022},"ram":0.0516285,"disk":0,"timestamp":"2024-04-11T13:55:11Z"},{"name":"opennebula-worker-1","cpu":{"cores":[0.0176,0.0101,0.0202,0.0099,0.0303],"average":0.01762},"ram":0.0520297,"disk":0.792,"timestamp":"2024-04-11T13:55:13Z"},{"name":"opennebula-worker-1","cpu":{"cores":[0.015,0.0098,0.0202,0.0099,0.0202],"average":0.01502},"ram":0.0529224,"disk":0.284,"timestamp":"2024-04-11T13:55:15Z"},{"name":"opennebula-worker-1","cpu":{"cores":[0.0792,0.0792,0.0686,0.1386,0.03],"average":0.07912000000000001},"ram":0.0529974,"disk":0.08,"timestamp":"2024-04-11T13:55:17Z"},{"name":"opennebula-worker-1","cpu":{"cores":[0.0249,0.05,0.05,0,0],"average":0.02498},"ram":0.0541226,"disk":0.008,"timestamp":"2024-04-11T13:55:20Z"},{"name":"opennebula-worker-1","cpu":{"cores":[0.0275,0.0098,0.0204,0.03,0.05],"average":0.02754},"ram":0.0540759,"disk":0.26,"timestamp":"2024-04-11T13:55:22Z"},{"name":"opennebula-worker-1","cpu":{"cores":[0.1975,0.1959,0.4141,0.049,0.134],"average":0.1981},"ram":0.0538043,"disk":0.036,"timestamp":"2024-04-11T13:55:24Z"},{"name":"opennebula-worker-1","cpu":{"cores":[0.0419,0.0816,0.0303,0.03,0.0275],"average":0.04226},"ram":0.0564878,"disk":0.084,"timestamp":"2024-04-11T13:55:26Z"},{"name":"opennebula-worker-1","cpu":{"cores":[0.0744,0.0784,0.15,0.05,0.0198],"average":0.07451999999999999},"ram":0.0630948,"disk":0.564,"timestamp":"2024-04-11T13:55:28Z"},{"name":"opennebula-worker-1","cpu":{"cores":[0.0246,0.0467,0.05,0,0],"average":0.02426},"ram":0.0633541,"disk":0.004,"timestamp":"2024-04-11T13:55:30Z"},{"name":"opennebula-worker-1","cpu":{"cores":[0.0614,0.0392,0,0.0777,0.1275],"average":0.061160000000000006},"ram":0.0634465,"disk":0.012,"timestamp":"2024-04-11T13:55:32Z"},{"name":"opennebula-worker-1","cpu":{"cores":[0.0325,0.0495,0.0404,0.01,0.03],"average":0.03248},"ram":0.0645238,"disk":0.14,"timestamp":"2024-04-11T13:55:34Z"},{"name":"opennebula-worker-1","cpu":{"cores":[0.0223,0.049,0.0392,0,0],"average":0.0221},"ram":0.0631771,"disk":0.048,"timestamp":"2024-04-11T13:55:36Z"},{"name":"opennebula-worker-1","cpu":{"cores":[0.0302,0.01,0,0.0707,0.04],"average":0.030180000000000002},"ram":0.0631859,"disk":0.008,"timestamp":"2024-04-11T13:55:39Z"},{"name":"opennebula-worker-1","cpu":{"cores":[0.1219,0.0297,0.0784,0.1386,0.2449],"average":0.12269999999999999},"ram":0.0625509,"disk":0.016,"timestamp":"2024-04-11T13:55:41Z"},{"name":"opennebula-worker-1","cpu":{"cores":[0.1166,0.0404,0.0297,0.33,0.068],"average":0.11694},"ram":0.0627802,"disk":0.048,"timestamp":"2024-04-11T13:55:43Z"},{"name":"opennebula-worker-1","cpu":{"cores":[0.149,0.1327,0.09,0.22,0.1531],"average":0.14896},"ram":0.0663695,"disk":0.7,"timestamp":"2024-04-11T13:55:45Z"},{"name":"opennebula-worker-1","cpu":{"cores":[0.0326,0.02,0.01,0.01,0.0909],"average":0.03269999999999999},"ram":0.0718381,"disk":0.392,"timestamp":"2024-04-11T13:55:47Z"},{"name":"opennebula-worker-1","cpu":{"cores":[0.0174,0.0505,0,0,0.02],"average":0.017580000000000002},"ram":0.0749403,"disk":0.052,"timestamp":"2024-04-11T13:55:49Z"},{"name":"opennebula-worker-1","cpu":{"cores":[0.0173,0.02,0,0.0192,0.0297],"average":0.01724},"ram":0.0738399,"disk":0.008,"timestamp":"2024-04-11T13:55:51Z"},{"name":"opennebula-worker-1","cpu":{"cores":[0.0249,0,0,0.0577,0.04],"average":0.024520000000000004},"ram":0.0738699,"disk":0.064,"timestamp":"2024-04-11T13:55:53Z"},{"name":"opennebula-worker-1","cpu":{"cores":[0.1106,0.1856,0.1748,0.0408,0.04],"average":0.11036000000000001},"ram":0.0742156,"disk":0.112,"timestamp":"2024-04-11T13:55:55Z"},{"name":"opennebula-worker-1","cpu":{"cores":[0.0371,0.0297,0.0294,0.0693,0.02],"average":0.037099999999999994},"ram":0.0733116,"disk":0.032,"timestamp":"2024-04-11T13:55:57Z"},{"name":"opennebula-worker-1","cpu":{"cores":[0.1253,0.0734,0.0297,0.2917,0.1188],"average":0.12778},"ram":0.0752889,"disk":0.044,"timestamp":"2024-04-11T13:56:00Z"},{"name":"opennebula-worker-1","cpu":{"cores":[0.0606,0.0909,0.1,0.0404,0.0102],"average":0.060419999999999995},"ram":0.0840091,"disk":0.164,"timestamp":"2024-04-11T13:56:02Z"},{"name":"opennebula-worker-1","cpu":{"cores":[0.0453,0.07,0.04,0.0505,0.0204],"average":0.04524000000000001},"ram":0.0848793,"disk":0.752,"timestamp":"2024-04-11T13:56:04Z"},{"name":"opennebula-worker-1","cpu":{"cores":[0.0253,0.0408,0.06,0,0],"average":0.02522},"ram":0.0836938,"disk":0.004,"timestamp":"2024-04-11T13:56:06Z"},{"name":"opennebula-worker-1","cpu":{"cores":[0.0252,0.0505,0.0505,0,0],"average":0.025240000000000002},"ram":0.0833305,"disk":0.016,"timestamp":"2024-04-11T13:56:08Z"},{"name":"opennebula-worker-1","cpu":{"cores":[0.0223,0.04,0.0099,0.0097,0.03],"average":0.02238},"ram":0.0838399,"disk":0.052,"timestamp":"2024-04-11T13:56:10Z"},{"name":"opennebula-worker-1","cpu":{"cores":[0.0831,0.0909,0.0606,0.1111,0.07],"average":0.08314},"ram":0.083881,"disk":0.144,"timestamp":"2024-04-11T13:56:12Z"},{"name":"opennebula-worker-1","cpu":{"cores":[0.0609,0.0102,0.0101,0.1633,0.0606],"average":0.06102},"ram":0.083506,"disk":0.296,"timestamp":"2024-04-11T13:56:14Z"},{"name":"opennebula-worker-1","cpu":{"cores":[0.0175,0.03,0.02,0.0202,0],"average":0.01754},"ram":0.0840998,"disk":0.012,"timestamp":"2024-04-11T13:56:16Z"},{"name":"opennebula-worker-1","cpu":{"cores":[0.2085,0.3776,0.03,0.3168,0.1111],"average":0.2088},"ram":0.0844593,"disk":0.032,"timestamp":"2024-04-11T13:56:19Z"},{"name":"opennebula-worker-1","cpu":{"cores":[0.0399,0,0.0202,0.1,0.04],"average":0.04002000000000001},"ram":0.0900685,"disk":0.012,"timestamp":"2024-04-11T13:56:21Z"},{"name":"opennebula-worker-1","cpu":{"cores":[0.1054,0.0833,0.2396,0.0408,0.0606],"average":0.10594},"ram":0.0948244,"disk":0.808,"timestamp":"2024-04-11T13:56:23Z"},{"name":"opennebula-worker-1","cpu":{"cores":[0.0251,0.05,0.05,0,0],"average":0.025019999999999997},"ram":0.0940351,"disk":0.012,"timestamp":"2024-04-11T13:56:25Z"},{"name":"opennebula-worker-1","cpu":{"cores":[0.0175,0.03,0.01,0.0202,0.01],"average":0.01754},"ram":0.094347,"disk":0.004,"timestamp":"2024-04-11T13:56:27Z"},{"name":"opennebula-worker-1","cpu":{"cores":[0.0723,0.0485,0.1633,0.0306,0.049],"average":0.07274},"ram":0.0951632,"disk":0.204,"timestamp":"2024-04-11T13:56:29Z"},{"name":"opennebula-worker-1","cpu":{"cores":[0.1893,0.2653,0.2188,0.0619,0.21],"average":0.18905999999999998},"ram":0.095303,"disk":0.16,"timestamp":"2024-04-11T13:56:31Z"},{"name":"opennebula-worker-1","cpu":{"cores":[0.1053,0.2255,0.0495,0.101,0.0412],"average":0.1045},"ram":0.102026,"disk":0.016,"timestamp":"2024-04-11T13:56:33Z"},{"name":"opennebula-worker-1","cpu":{"cores":[0.0253,0.03,0.0408,0,0.03],"average":0.02522},"ram":0.102771,"disk":0.64,"timestamp":"2024-04-11T13:56:35Z"},{"name":"opennebula-worker-1","cpu":{"cores":[0.0226,0,0,0.0505,0.04],"average":0.02262},"ram":0.103876,"disk":0.008,"timestamp":"2024-04-11T13:56:38Z"},{"name":"opennebula-worker-1","cpu":{"cores":[0.0945,0,0.165,0.13,0.08],"average":0.09390000000000001},"ram":0.103922,"disk":0.152,"timestamp":"2024-04-11T13:56:40Z"},{"name":"opennebula-worker-1","cpu":{"cores":[0.0276,0.051,0.0606,0,0],"average":0.027839999999999997},"ram":0.103511,"disk":0.136,"timestamp":"2024-04-11T13:56:42Z"},{"name":"opennebula-worker-1","cpu":{"cores":[0.0101,0.0202,0,0,0.0204],"average":0.01014},"ram":0.103856,"disk":0.008,"timestamp":"2024-04-11T13:56:44Z"},{"name":"opennebula-worker-1","cpu":{"cores":[0.2672,0.4796,0.29,0.1771,0.1212],"average":0.26702},"ram":0.106572,"disk":0.304,"timestamp":"2024-04-11T13:56:46Z"},{"name":"opennebula-worker-1","cpu":{"cores":[0.0424,0.06,0.0101,0.0495,0.0495],"average":0.04229999999999999},"ram":0.108102,"disk":0.008,"timestamp":"2024-04-11T13:56:48Z"},{"name":"opennebula-worker-1","cpu":{"cores":[0.0329,0.051,0.0102,0.0408,0.0297],"average":0.032920000000000005},"ram":0.113105,"disk":0.744,"timestamp":"2024-04-11T13:56:50Z"},{"name":"opennebula-worker-1","cpu":{"cores":[0.0151,0.0297,0.0101,0,0.0204],"average":0.01506},"ram":0.113178,"disk":0.044,"timestamp":"2024-04-11T13:56:52Z"},{"name":"opennebula-worker-1","cpu":{"cores":[0.025,0.04,0.0594,0,0],"average":0.024880000000000003},"ram":0.113269,"disk":0.008,"timestamp":"2024-04-11T13:56:54Z"},{"name":"opennebula-worker-1","cpu":{"cores":[0.1184,0.0909,0.2255,0.08,0.0729],"average":0.11753999999999998},"ram":0.113144,"disk":0.212,"timestamp":"2024-04-11T13:56:57Z"},{"name":"opennebula-worker-1","cpu":{"cores":[0.0251,0.05,0.0404,0,0.0099],"average":0.025079999999999998},"ram":0.113693,"disk":0.012,"timestamp":"2024-04-11T13:56:59Z"},{"name":"opennebula-worker-1","cpu":{"cores":[0.1949,0.0808,0.0505,0.5859,0.0612],"average":0.19466},"ram":0.115193,"disk":0.04,"timestamp":"2024-04-11T13:57:01Z"},{"name":"opennebula-worker-1","cpu":{"cores":[0.0655,0.0505,0.06,0.0606,0.0909],"average":0.06549999999999999},"ram":0.120196,"disk":0.216,"timestamp":"2024-04-11T13:57:03Z"},{"name":"opennebula-worker-1","cpu":{"cores":[0.0428,0.0396,0.0515,0.04,0.0404],"average":0.042859999999999995},"ram":0.123965,"disk":0.652,"timestamp":"2024-04-11T13:57:05Z"},{"name":"opennebula-worker-1","cpu":{"cores":[0.0848,0.01,0.0891,0.0891,0.1515],"average":0.0849},"ram":0.12393,"disk":0.032,"timestamp":"2024-04-11T13:57:07Z"},{"name":"opennebula-worker-1","cpu":{"cores":[0.1106,0.08,0.0404,0.1,0.2222],"average":0.11063999999999999},"ram":0.077925,"disk":0.348,"timestamp":"2024-04-11T13:57:09Z"},{"name":"opennebula-worker-1","cpu":{"cores":[0.2577,0.2887,0.2062,0.2857,0.25],"average":0.25766},"ram":0.0756326,"disk":0.38,"timestamp":"2024-04-11T13:57:11Z"},{"name":"opennebula-worker-1","cpu":{"cores":[0.0499,0.0198,0.0099,0.03,0.1414],"average":0.0502},"ram":0.024324,"disk":0.412,"timestamp":"2024-04-11T13:57:13Z"},{"name":"opennebula-worker-1","cpu":{"cores":[0.0249,0,0,0.05,0.0495],"average":0.02488},"ram":0.0231825,"disk":0.012,"timestamp":"2024-04-11T13:57:16Z"},{"name":"opennebula-worker-1","cpu":{"cores":[0.0251,0.05,0.05,0,0],"average":0.025019999999999997},"ram":0.0232685,"disk":0.612,"timestamp":"2024-04-11T13:57:18Z"},{"name":"opennebula-worker-1","cpu":{"cores":[0.0252,0,0,0.05,0.0505],"average":0.025140000000000003},"ram":0.0230329,"disk":0.024,"timestamp":"2024-04-11T13:57:20Z"},{"name":"opennebula-worker-1","cpu":{"cores":[0.0125,0.02,0,0,0.0297],"average":0.012440000000000001},"ram":0.02317,"disk":0.056,"timestamp":"2024-04-11T13:57:22Z"},{"name":"opennebula-worker-1","cpu":{"cores":[0.0575,0.05,0.1782,0,0],"average":0.05714},"ram":0.0232473,"disk":0.168,"timestamp":"2024-04-11T13:57:24Z"},{"name":"opennebula-worker-1","cpu":{"cores":[0.0176,0.0297,0,0.02,0.0204],"average":0.01754},"ram":0.0227916,"disk":0.024,"timestamp":"2024-04-11T13:57:26Z"},{"name":"opennebula-worker-1","cpu":{"cores":[0.0174,0.0099,0.03,0,0.0297],"average":0.0174},"ram":0.0231111,"disk":0.004,"timestamp":"2024-04-11T13:57:28Z"},{"name":"opennebula-worker-1","cpu":{"cores":[0.0125,0,0.02,0,0.0297],"average":0.012440000000000001},"ram":0.0245123,"disk":0.216,"timestamp":"2024-04-11T13:57:30Z"},{"name":"opennebula-worker-1","cpu":{"cores":[0.025,0.0594,0.0404,0,0],"average":0.02496},"ram":0.0230842,"disk":0.016,"timestamp":"2024-04-11T13:57:32Z"},{"name":"opennebula-worker-1","cpu":{"cores":[0.0543,0.0096,0.02,0.0495,0.14],"average":0.054680000000000006},"ram":0.0231141,"disk":0.028,"timestamp":"2024-04-11T13:57:34Z"},{"name":"opennebula-worker-1","cpu":{"cores":[0.0175,0.03,0.0099,0.0202,0.0101],"average":0.01754},"ram":0.0245413,"disk":0.008,"timestamp":"2024-04-11T13:57:37Z"},{"name":"opennebula-worker-1","cpu":{"cores":[0.0276,0.01,0,0.05,0.05],"average":0.02752},"ram":0.0232483,"disk":0.012,"timestamp":"2024-04-11T13:57:39Z"},{"name":"opennebula-worker-1","cpu":{"cores":[0.0526,0.11,0,0.0594,0.0408],"average":0.05256000000000001},"ram":0.023294,"disk":0.148,"timestamp":"2024-04-11T13:57:41Z"},{"name":"opennebula-worker-1","cpu":{"cores":[0.0224,0.04,0.0495,0,0],"average":0.02238},"ram":0.0229674,"disk":0.008,"timestamp":"2024-04-11T13:57:43Z"},{"name":"opennebula-worker-1","cpu":{"cores":[0.0249,0.0099,0,0.04,0.05],"average":0.024960000000000003},"ram":0.0230287,"disk":0.016,"timestamp":"2024-04-11T13:57:45Z"},{"name":"opennebula-worker-1","cpu":{"cores":[0.02,0.0404,0.04,0,0],"average":0.020079999999999997},"ram":0.0228591,"disk":0.008,"timestamp":"2024-04-11T13:57:47Z"},{"name":"opennebula-worker-1","cpu":{"cores":[0.0276,0,0,0.06,0.05],"average":0.02752},"ram":0.0247411,"disk":0.016,"timestamp":"2024-04-11T13:57:49Z"},{"name":"opennebula-worker-2","cpu":{"cores":[0.0474,0.01,0.14,0.02,0.0198],"average":0.04744},"ram":0.0247985,"disk":0.004,"timestamp":"2024-04-11T13:54:00Z"},{"name":"opennebula-worker-2","cpu":{"cores":[0.0251,0.0505,0.0404,0.01,0],"average":0.0252},"ram":0.024437,"disk":0.016,"timestamp":"2024-04-11T13:54:02Z"},{"name":"opennebula-worker-2","cpu":{"cores":[0.0274,0,0.0099,0.05,0.05],"average":0.027460000000000002},"ram":0.0243776,"disk":0.012,"timestamp":"2024-04-11T13:54:04Z"},{"name":"opennebula-worker-2","cpu":{"cores":[0.0274,0.05,0.05,0,0.01],"average":0.027480000000000004},"ram":0.024778,"disk":0.012,"timestamp":"2024-04-11T13:54:06Z"},{"name":"opennebula-worker-2","cpu":{"cores":[0.0226,0,0,0.04,0.0505],"average":0.02262},"ram":0.0247934,"disk":0.016,"timestamp":"2024-04-11T13:54:08Z"},{"name":"opennebula-worker-2","cpu":{"cores":[0.0575,0.13,0,0.05,0.05],"average":0.057499999999999996},"ram":0.0247929,"disk":0.012,"timestamp":"2024-04-11T13:54:10Z"},{"name":"opennebula-worker-2","cpu":{"cores":[0.0226,0.05,0.0404,0,0],"average":0.0226},"ram":0.0238926,"disk":0.024,"timestamp":"2024-04-11T13:54:12Z"},{"name":"opennebula-worker-2","cpu":{"cores":[0.0299,0.0495,0.0588,0,0.0101],"average":0.02966},"ram":0.0245186,"disk":0.008,"timestamp":"2024-04-11T13:54:14Z"},{"name":"opennebula-worker-2","cpu":{"cores":[0.0226,0.0404,0.05,0,0],"average":0.022600000000000002},"ram":0.0232766,"disk":0.008,"timestamp":"2024-04-11T13:54:16Z"},{"name":"opennebula-worker-2","cpu":{"cores":[0.0252,0.0505,0.05,0,0],"average":0.025140000000000003},"ram":0.0233375,"disk":0.012,"timestamp":"2024-04-11T13:54:19Z"},{"name":"opennebula-worker-2","cpu":{"cores":[0.0528,0.02,0.05,0.0202,0.1212],"average":0.05284},"ram":0.0233683,"disk":0.008,"timestamp":"2024-04-11T13:54:21Z"},{"name":"opennebula-worker-2","cpu":{"cores":[0.015,0.0297,0.01,0,0.02],"average":0.01494},"ram":0.0230121,"disk":0.008,"timestamp":"2024-04-11T13:54:23Z"},{"name":"opennebula-worker-2","cpu":{"cores":[0.0251,0,0,0.05,0.05],"average":0.025019999999999997},"ram":0.0230424,"disk":0.012,"timestamp":"2024-04-11T13:54:25Z"},{"name":"opennebula-worker-2","cpu":{"cores":[0.0275,0.05,0.05,0.01,0],"average":0.027500000000000004},"ram":0.0229197,"disk":0.016,"timestamp":"2024-04-11T13:54:27Z"},{"name":"opennebula-worker-2","cpu":{"cores":[0.025,0,0.01,0.05,0.04],"average":0.025},"ram":0.0230234,"disk":0.028,"timestamp":"2024-04-11T13:54:29Z"},{"name":"opennebula-worker-2","cpu":{"cores":[0.0603,0.06,0.18,0,0],"average":0.06006},"ram":0.0230842,"disk":0.012,"timestamp":"2024-04-11T13:54:31Z"},{"name":"opennebula-worker-2","cpu":{"cores":[0.0404,0.051,0.0306,0.04,0.04],"average":0.040400000000000005},"ram":0.0235758,"disk":0.384,"timestamp":"2024-04-11T13:54:33Z"},{"name":"opennebula-worker-2","cpu":{"cores":[0.0957,0.1122,0.1188,0.051,0.1],"average":0.09554},"ram":0.026569,"disk":0.512,"timestamp":"2024-04-11T13:54:35Z"},{"name":"opennebula-worker-2","cpu":{"cores":[0.0451,0.0396,0.0404,0.01,0.0909],"average":0.0452},"ram":0.0318025,"disk":0.004,"timestamp":"2024-04-11T13:54:38Z"},{"name":"opennebula-worker-2","cpu":{"cores":[0.0176,0,0.04,0,0.0303],"average":0.017580000000000002},"ram":0.034692,"disk":0.1,"timestamp":"2024-04-11T13:54:40Z"},{"name":"opennebula-worker-2","cpu":{"cores":[0.0673,0.13,0.0198,0.06,0.06],"average":0.06742000000000001},"ram":0.0347541,"disk":0.036,"timestamp":"2024-04-11T13:54:42Z"},{"name":"opennebula-worker-2","cpu":{"cores":[0.0882,0.1414,0.101,0.0612,0.0495],"average":0.08825999999999999},"ram":0.0350609,"disk":0.476,"timestamp":"2024-04-11T13:54:44Z"},{"name":"opennebula-worker-2","cpu":{"cores":[0.0324,0.03,0,0.0495,0.05],"average":0.03238},"ram":0.0344001,"disk":0.008,"timestamp":"2024-04-11T13:54:46Z"},{"name":"opennebula-worker-2","cpu":{"cores":[0.0299,0.01,0.0099,0.05,0.05],"average":0.029959999999999997},"ram":0.0340655,"disk":0.012,"timestamp":"2024-04-11T13:54:48Z"},{"name":"opennebula-worker-2","cpu":{"cores":[0.0528,0.0495,0.0707,0.051,0.04],"average":0.05279999999999999},"ram":0.0346284,"disk":0.352,"timestamp":"2024-04-11T13:54:50Z"},{"name":"opennebula-worker-2","cpu":{"cores":[0.1342,0.1111,0.0928,0.1717,0.16],"average":0.13396000000000002},"ram":0.0373654,"disk":0.348,"timestamp":"2024-04-11T13:54:52Z"},{"name":"opennebula-worker-2","cpu":{"cores":[0.0399,0.0202,0,0.0792,0.06],"average":0.03986},"ram":0.0419609,"disk":0.008,"timestamp":"2024-04-11T13:54:54Z"},{"name":"opennebula-worker-2","cpu":{"cores":[0.0376,0.0594,0.0606,0.0202,0.01],"average":0.03756},"ram":0.0445447,"disk":0.508,"timestamp":"2024-04-11T13:54:57Z"},{"name":"opennebula-worker-2","cpu":{"cores":[0.025,0,0,0.05,0.05],"average":0.025},"ram":0.0438099,"disk":0.008,"timestamp":"2024-04-11T13:54:59Z"},{"name":"opennebula-worker-2","cpu":{"cores":[0.0299,0.01,0,0.06,0.0495],"average":0.029879999999999997},"ram":0.0438561,"disk":0.02,"timestamp":"2024-04-11T13:55:01Z"},{"name":"opennebula-worker-2","cpu":{"cores":[0.0914,0.049,0,0.17,0.1485],"average":0.09178},"ram":0.0443469,"disk":0.088,"timestamp":"2024-04-11T13:55:03Z"},{"name":"opennebula-worker-2","cpu":{"cores":[0.0275,0,0.0198,0.05,0.0404],"average":0.02754},"ram":0.0431059,"disk":0.016,"timestamp":"2024-04-11T13:55:05Z"},{"name":"opennebula-worker-2","cpu":{"cores":[0.0456,0.08,0.0612,0.0204,0.0202],"average":0.04548},"ram":0.0431367,"disk":0.032,"timestamp":"2024-04-11T13:55:07Z"},{"name":"opennebula-worker-2","cpu":{"cores":[0.1168,0.1122,0.099,0.2347,0.0206],"average":0.11665999999999999},"ram":0.0443154,"disk":0.148,"timestamp":"2024-04-11T13:55:09Z"},{"name":"opennebula-worker-2","cpu":{"cores":[0.0397,0.0196,0.0101,0.0588,0.07],"average":0.03964},"ram":0.0508798,"disk":0.008,"timestamp":"2024-04-11T13:55:11Z"},{"name":"opennebula-worker-2","cpu":{"cores":[0.1411,0.101,0.1089,0.1122,0.2424],"average":0.14112},"ram":0.0519627,"disk":0.5,"timestamp":"2024-04-11T13:55:13Z"},{"name":"opennebula-worker-2","cpu":{"cores":[0.02,0,0,0.0495,0.0404],"average":0.02198},"ram":0.0538222,"disk":0.144,"timestamp":"2024-04-11T13:55:15Z"},{"name":"opennebula-worker-2","cpu":{"cores":[0.0274,0.0198,0.01,0.05,0.0297],"average":0.027380000000000005},"ram":0.052398,"disk":0.012,"timestamp":"2024-04-11T13:55:18Z"},{"name":"opennebula-worker-2","cpu":{"cores":[0.0252,0.0101,0.01,0.0404,0.0404],"average":0.02522},"ram":0.0523088,"disk":0.004,"timestamp":"2024-04-11T13:55:20Z"},{"name":"opennebula-worker-2","cpu":{"cores":[0.0698,0.0198,0,0.1863,0.0693],"average":0.06903999999999999},"ram":0.0524161,"disk":0.216,"timestamp":"2024-04-11T13:55:22Z"},{"name":"opennebula-worker-2","cpu":{"cores":[0.1883,0.1684,0.2626,0.24,0.0808],"average":0.18802},"ram":0.0537007,"disk":0.128,"timestamp":"2024-04-11T13:55:24Z"},{"name":"opennebula-worker-2","cpu":{"cores":[0.0451,0.09,0.07,0.02,0],"average":0.04502},"ram":0.0607085,"disk":0.004,"timestamp":"2024-04-11T13:55:26Z"},{"name":"opennebula-worker-2","cpu":{"cores":[0.0176,0.0101,0.05,0.02,0],"average":0.019540000000000002},"ram":0.063819,"disk":0.588,"timestamp":"2024-04-11T13:55:28Z"},{"name":"opennebula-worker-2","cpu":{"cores":[0.0152,0.0204,0,0.0101,0.03],"average":0.015139999999999997},"ram":0.0643145,"disk":0.012,"timestamp":"2024-04-11T13:55:30Z"},{"name":"opennebula-worker-2","cpu":{"cores":[0.0274,0.0099,0,0.05,0.05],"average":0.027460000000000002},"ram":0.0643407,"disk":0.008,"timestamp":"2024-04-11T13:55:33Z"},{"name":"opennebula-worker-2","cpu":{"cores":[0.0785,0.1818,0.06,0.0408,0.0306],"average":0.07833999999999999},"ram":0.0643739,"disk":0.088,"timestamp":"2024-04-11T13:55:35Z"},{"name":"opennebula-worker-2","cpu":{"cores":[0.025,0,0,0.06,0.04],"average":0.025},"ram":0.0637279,"disk":0.016,"timestamp":"2024-04-11T13:55:37Z"},{"name":"opennebula-worker-2","cpu":{"cores":[0.028,0.0408,0.051,0.0102,0.0101],"average":0.02802},"ram":0.0637587,"disk":0.352,"timestamp":"2024-04-11T13:55:39Z"},{"name":"opennebula-worker-2","cpu":{"cores":[0.1633,0.0309,0.5556,0.0206,0.0404],"average":0.16216},"ram":0.0653167,"disk":0.116,"timestamp":"2024-04-11T13:55:41Z"},{"name":"opennebula-worker-2","cpu":{"cores":[0.0574,0.0102,0.0198,0.0707,0.1262],"average":0.05686},"ram":0.0659127,"disk":0.204,"timestamp":"2024-04-11T13:55:43Z"},{"name":"opennebula-worker-2","cpu":{"cores":[0.0806,0.1837,0.0707,0.0202,0.0495],"average":0.08093999999999998},"ram":0.073011,"disk":0.636,"timestamp":"2024-04-11T13:55:45Z"},{"name":"opennebula-worker-2","cpu":{"cores":[0.0125,0.03,0,0.02,0],"average":0.0125},"ram":0.07258,"disk":0.008,"timestamp":"2024-04-11T13:55:47Z"},{"name":"opennebula-worker-2","cpu":{"cores":[0.0226,0,0,0.0495,0.0404],"average":0.0225},"ram":0.072595,"disk":0.008,"timestamp":"2024-04-11T13:55:49Z"},{"name":"opennebula-worker-2","cpu":{"cores":[0.0779,0,0.1515,0.0909,0.07],"average":0.07805999999999999},"ram":0.0726206,"disk":0.144,"timestamp":"2024-04-11T13:55:51Z"},{"name":"opennebula-worker-2","cpu":{"cores":[0.0452,0,0.0404,0.0202,0.12],"average":0.04516},"ram":0.073372,"disk":0.008,"timestamp":"2024-04-11T13:55:54Z"},{"name":"opennebula-worker-2","cpu":{"cores":[0.02,0,0.0396,0.0392,0],"average":0.01976},"ram":0.0729416,"disk":0.244,"timestamp":"2024-04-11T13:55:56Z"},{"name":"opennebula-worker-2","cpu":{"cores":[0.0224,0.0404,0.0098,0.02,0.02],"average":0.022520000000000002},"ram":0.075086,"disk":0.54,"timestamp":"2024-04-11T13:55:58Z"},{"name":"opennebula-worker-2","cpu":{"cores":[0.0907,0.14,0.1068,0.0417,0.0714],"average":0.09012},"ram":0.0752872,"disk":0.308,"timestamp":"2024-04-11T13:56:00Z"},{"name":"opennebula-worker-2","cpu":{"cores":[0.0812,0.0606,0.0612,0.0306,0.1717],"average":0.08106},"ram":0.0811198,"disk":0.048,"timestamp":"2024-04-11T13:56:02Z"},{"name":"opennebula-worker-2","cpu":{"cores":[0.0278,0.0606,0.0408,0.0101,0],"average":0.027860000000000003},"ram":0.0823564,"disk":0.396,"timestamp":"2024-04-11T13:56:04Z"},{"name":"opennebula-worker-2","cpu":{"cores":[0.0151,0.02,0.01,0,0.0303],"average":0.01508},"ram":0.0827854,"disk":0.004,"timestamp":"2024-04-11T13:56:06Z"},{"name":"opennebula-worker-2","cpu":{"cores":[0.0932,0.1111,0.09,0.0808,0.0909],"average":0.09319999999999999},"ram":0.0826268,"disk":0.148,"timestamp":"2024-04-11T13:56:08Z"},{"name":"opennebula-worker-2","cpu":{"cores":[0.0584,0.051,0.0918,0.0206,0.0693],"average":0.05822000000000001},"ram":0.0839358,"disk":0.344,"timestamp":"2024-04-11T13:56:10Z"},{"name":"opennebula-worker-2","cpu":{"cores":[0.0251,0,0,0.0505,0.0495],"average":0.025019999999999997},"ram":0.0827339,"disk":0.016,"timestamp":"2024-04-11T13:56:13Z"},{"name":"opennebula-worker-2","cpu":{"cores":[0.1053,0.16,0.0303,0.101,0.1287],"average":0.10506},"ram":0.0825491,"disk":0.02,"timestamp":"2024-04-11T13:56:15Z"},{"name":"opennebula-worker-2","cpu":{"cores":[0.025,0,0,0.0505,0.05],"average":0.0251},"ram":0.08308,"disk":0.012,"timestamp":"2024-04-11T13:56:17Z"},{"name":"opennebula-worker-2","cpu":{"cores":[0.2766,0.2755,0.1287,0.5204,0.1856],"average":0.27736},"ram":0.0835349,"disk":0.072,"timestamp":"2024-04-11T13:56:19Z"},{"name":"opennebula-worker-2","cpu":{"cores":[0.0499,0.049,0.0404,0.11,0],"average":0.04986},"ram":0.0873487,"disk":0,"timestamp":"2024-04-11T13:56:21Z"},{"name":"opennebula-worker-2","cpu":{"cores":[0.0221,0.0099,0.0463,0,0.0303],"average":0.02172},"ram":0.0920082,"disk":0.768,"timestamp":"2024-04-11T13:56:23Z"},{"name":"opennebula-worker-2","cpu":{"cores":[0.0611,0.028,0.0404,0.0882,0.0891],"average":0.061360000000000005},"ram":0.0940207,"disk":0.152,"timestamp":"2024-04-11T13:56:25Z"},{"name":"opennebula-worker-2","cpu":{"cores":[0.0199,0.0099,0.0297,0.0396,0],"average":0.019819999999999997},"ram":0.0924797,"disk":0.004,"timestamp":"2024-04-11T13:56:27Z"},{"name":"opennebula-worker-2","cpu":{"cores":[0.0501,0.02,0.05,0.0098,0.1237],"average":0.05072},"ram":0.0927713,"disk":0.204,"timestamp":"2024-04-11T13:56:29Z"},{"name":"opennebula-worker-2","cpu":{"cores":[0.1925,0.1856,0.4646,0.0392,0.0882],"average":0.19402},"ram":0.0928322,"disk":0.036,"timestamp":"2024-04-11T13:56:32Z"},{"name":"opennebula-worker-2","cpu":{"cores":[0.0274,0.02,0.0098,0.0303,0.05],"average":0.027500000000000004},"ram":0.0984499,"disk":0.06,"timestamp":"2024-04-11T13:56:34Z"},{"name":"opennebula-worker-2","cpu":{"cores":[0.0354,0.0408,0.0204,0.0396,0.0404],"average":0.035320000000000004},"ram":0.103242,"disk":0.924,"timestamp":"2024-04-11T13:56:36Z"},{"name":"opennebula-worker-2","cpu":{"cores":[0.0301,0.0505,0.0594,0,0.0099],"average":0.02998},"ram":0.10231,"disk":0.004,"timestamp":"2024-04-11T13:56:38Z"},{"name":"opennebula-worker-2","cpu":{"cores":[0.015,0,0.03,0.02,0.0101],"average":0.01502},"ram":0.102341,"disk":0.028,"timestamp":"2024-04-11T13:56:41Z"},{"name":"opennebula-worker-2","cpu":{"cores":[0.0075,0.01,0.01,0,0.01],"average":0.0075000000000000015},"ram":0.102616,"disk":0.036,"timestamp":"2024-04-11T13:56:43Z"},{"name":"opennebula-worker-2","cpu":{"cores":[0.1708,0.2596,0.09,0.1414,0.1881],"average":0.16997999999999996},"ram":0.102771,"disk":0.268,"timestamp":"2024-04-11T13:56:45Z"},{"name":"opennebula-worker-2","cpu":{"cores":[0.2245,0.2222,0.1919,0.23,0.2553],"average":0.22477999999999998},"ram":0.105566,"disk":0.96,"timestamp":"2024-04-11T13:56:47Z"},{"name":"opennebula-worker-2","cpu":{"cores":[0.0402,0.0612,0.07,0.03,0],"average":0.040279999999999996},"ram":0.109821,"disk":0.012,"timestamp":"2024-04-11T13:56:49Z"},{"name":"opennebula-worker-2","cpu":{"cores":[0.0202,0.0404,0,0.02,0.0202],"average":0.02016},"ram":0.112606,"disk":0.464,"timestamp":"2024-04-11T13:56:51Z"},{"name":"opennebula-worker-2","cpu":{"cores":[0.0655,0.0103,0.0606,0.0707,0.1176],"average":0.06494},"ram":0.114209,"disk":0.192,"timestamp":"2024-04-11T13:56:53Z"},{"name":"opennebula-worker-2","cpu":{"cores":[0.0347,0.07,0.0594,0.0099,0],"average":0.034800000000000005},"ram":0.112673,"disk":0.012,"timestamp":"2024-04-11T13:56:55Z"},{"name":"opennebula-worker-2","cpu":{"cores":[0.0249,0,0,0.0594,0.0396],"average":0.024780000000000003},"ram":0.112676,"disk":0.008,"timestamp":"2024-04-11T13:56:57Z"},{"name":"opennebula-worker-2","cpu":{"cores":[0.0499,0.0792,0.0792,0.01,0.0303],"average":0.04972},"ram":0.112463,"disk":0.364,"timestamp":"2024-04-11T13:57:00Z"},{"name":"opennebula-worker-2","cpu":{"cores":[0.0714,0.09,0.0619,0.0606,0.0729],"average":0.07136},"ram":0.115665,"disk":0.604,"timestamp":"2024-04-11T13:57:02Z"},{"name":"opennebula-worker-2","cpu":{"cores":[0.1122,0.13,0.102,0.0388,0.18],"average":0.11259999999999999},"ram":0.120179,"disk":0.012,"timestamp":"2024-04-11T13:57:04Z"},{"name":"opennebula-worker-2","cpu":{"cores":[0.0224,0.0297,0,0.01,0.0485],"average":0.02212},"ram":0.121181,"disk":0.896,"timestamp":"2024-04-11T13:57:06Z"},{"name":"opennebula-worker-2","cpu":{"cores":[0.2231,0.2041,0.2404,0.13,0.3196],"average":0.22344},"ram":0.113968,"disk":0.536,"timestamp":"2024-04-11T13:57:08Z"},{"name":"opennebula-worker-2","cpu":{"cores":[0.2879,0.4536,0.3333,0.1765,0.1939],"average":0.28904},"ram":0.0715453,"disk":0.256,"timestamp":"2024-04-11T13:57:10Z"},{"name":"opennebula-worker-2","cpu":{"cores":[0.1108,0.1188,0.1818,0.101,0.0408],"average":0.11063999999999999},"ram":0.0323305,"disk":0.276,"timestamp":"2024-04-11T13:57:12Z"},{"name":"opennebula-worker-2","cpu":{"cores":[0.015,0.0297,0,0.03,0],"average":0.01494},"ram":0.0232023,"disk":0.02,"timestamp":"2024-04-11T13:57:14Z"},{"name":"opennebula-worker-2","cpu":{"cores":[0.0401,0.03,0,0.11,0.0198],"average":0.03998},"ram":0.0240459,"disk":0.044,"timestamp":"2024-04-11T13:57:17Z"},{"name":"opennebula-worker-2","cpu":{"cores":[0.0252,0.0505,0.05,0,0],"average":0.025140000000000003},"ram":0.0223319,"disk":0.016,"timestamp":"2024-04-11T13:57:19Z"},{"name":"opennebula-worker-2","cpu":{"cores":[0.062,0.0097,0.0198,0.0505,0.17],"average":0.06240000000000001},"ram":0.0224233,"disk":0.588,"timestamp":"2024-04-11T13:57:21Z"},{"name":"opennebula-worker-2","cpu":{"cores":[0.0275,0.05,0.06,0,0],"average":0.027500000000000004},"ram":0.0223512,"disk":0.008,"timestamp":"2024-04-11T13:57:23Z"},{"name":"opennebula-worker-2","cpu":{"cores":[0.0276,0.04,0.0505,0,0.02],"average":0.02762},"ram":0.022446,"disk":0.012,"timestamp":"2024-04-11T13:57:25Z"},{"name":"opennebula-worker-2","cpu":{"cores":[0.015,0,0.0297,0,0.03],"average":0.01494},"ram":0.02227,"disk":0.008,"timestamp":"2024-04-11T13:57:27Z"},{"name":"opennebula-worker-2","cpu":{"cores":[0.015,0.01,0.03,0,0.0202],"average":0.015040000000000001},"ram":0.0224484,"disk":0.016,"timestamp":"2024-04-11T13:57:29Z"},{"name":"opennebula-worker-2","cpu":{"cores":[0.0622,0.0606,0.165,0.02,0],"average":0.061560000000000004},"ram":0.0225254,"disk":0.24,"timestamp":"2024-04-11T13:57:31Z"},{"name":"opennebula-worker-2","cpu":{"cores":[0.0275,0,0,0.06,0.05],"average":0.027500000000000004},"ram":0.0225687,"disk":0.024,"timestamp":"2024-04-11T13:57:33Z"},{"name":"opennebula-worker-2","cpu":{"cores":[0.0276,0.0404,0.05,0.01,0.01],"average":0.027600000000000003},"ram":0.0225831,"disk":0.012,"timestamp":"2024-04-11T13:57:35Z"},{"name":"opennebula-worker-2","cpu":{"cores":[0.0277,0,0,0.0594,0.0505],"average":0.02752},"ram":0.023873,"disk":0.096,"timestamp":"2024-04-11T13:57:38Z"},{"name":"opennebula-worker-2","cpu":{"cores":[0.0252,0,0,0.05,0.0505],"average":0.025140000000000003},"ram":0.0225741,"disk":0.008,"timestamp":"2024-04-11T13:57:40Z"},{"name":"opennebula-worker-2","cpu":{"cores":[0.0501,0.0505,0.14,0,0.01],"average":0.05012},"ram":0.0226046,"disk":0.08,"timestamp":"2024-04-11T13:57:42Z"},{"name":"opennebula-worker-2","cpu":{"cores":[0.0275,0.01,0,0.0495,0.05],"average":0.0274},"ram":0.0230649,"disk":0.012,"timestamp":"2024-04-11T13:57:44Z"},{"name":"opennebula-worker-2","cpu":{"cores":[0.06,0.12,0.01,0.1089,0],"average":0.05978},"ram":0.0230957,"disk":0.004,"timestamp":"2024-04-11T13:57:46Z"},{"name":"opennebula-worker-2","cpu":{"cores":[0.0224,0,0,0.0404,0.0495],"average":0.02246},"ram":0.022676,"disk":0.008,"timestamp":"2024-04-11T13:57:48Z"},{"name":"opennebula-worker-2","cpu":{"cores":[0.1221,0.3131,0.09,0.0515,0.0309],"average":0.12152},"ram":0.0227525,"disk":0.436,"timestamp":"2024-04-11T13:57:50Z"}]}